hidden_py/__init__.py
hidden_py/dynamics.py
hidden_py/infer.py
hidden_py/log_setup.py
hidden_py/filters/__init__.py
hidden_py/filters/bayesian.py
hidden_py/optimize/__init__.py
hidden_py/optimize/base.py
hidden_py/optimize/config.py
hidden_py/optimize/optimization.py
hidden_py/optimize/registry.py
hidden_py/optimize/results.py
hidden_py/optimize/types.py
hidden_py-1.2.0.dist-info/LICENSE.txt
hidden_py-1.2.0.dist-info/METADATA
hidden_py-1.2.0.dist-info/WHEEL
hidden_py-1.2.0.dist-info/top_level.txt
hidden_py-1.2.0.dist-info/RECORD
