Metadata-Version: 2.1
Name: hidden-py
Version: 1.2.0
Summary: A python package for discrete-output hidden Markov models
Author: Steven Large
Author-email: stevelarge7@gmail.com
License: MIT
Project-URL: Source, https://github.com/StevenJLarge/hmm
Classifier: Development Status :: 3 - Alpha
Classifier: Intended Audience :: Science/Research
Classifier: License :: OSI Approved :: MIT License
Classifier: Programming Language :: Python
Classifier: Topic :: Scientific/Engineering :: Artificial Intelligence
Classifier: Topic :: Scientific/Engineering :: Physics
Classifier: Topic :: Scientific/Engineering :: Mathematics
License-File: LICENSE.txt
Requires-Dist: pytest
Requires-Dist: numpy
Requires-Dist: scipy
Requires-Dist: matplotlib
Requires-Dist: seaborn >=0.11.1
Requires-Dist: numba
Requires-Dist: loguru
